Metadata-Version: 2.1
Name: bagit-create
Version: 0.1.10.post1
Summary: Create BagIt packages harvesting data from upstream sources
Home-page: https://gitlab.cern.ch/digitalmemory/bagit-create
Author: Antonio Vivace
Author-email: antonio.vivace@cern.ch
License: GPLv3
Classifier: License :: OSI Approved :: GNU General Public License v3 (GPLv3)
Classifier: Programming Language :: Python :: 3
Classifier: Programming Language :: Python :: 3.7
Classifier: Programming Language :: Python :: 3.8
Classifier: Programming Language :: Python :: 3.9
Classifier: Programming Language :: Python :: 3.10
License-File: LICENSE
License-File: AUTHORS
Requires-Dist: appdirs (==1.4.4)
Requires-Dist: cernopendata-client (==0.2.0)
Requires-Dist: certifi (==2020.12.5)
Requires-Dist: chardet (==4.0.0)
Requires-Dist: click (>=7)
Requires-Dist: flake8 (==3.9.0)
Requires-Dist: fs (==2.4.12)
Requires-Dist: idna (==2.10)
Requires-Dist: mccabe (==0.6.1)
Requires-Dist: pycodestyle (==2.7.0)
Requires-Dist: pyflakes (==2.3.0)
Requires-Dist: pymarc (==4.0.0)
Requires-Dist: pytz (==2021.3)
Requires-Dist: requests (>=2.26)
Requires-Dist: six (==1.15.0)
Requires-Dist: urllib3 (==1.26.4)
Requires-Dist: bagit (==1.8.1)
Requires-Dist: checksumdir (==1.2.0)
Requires-Dist: jsonschema (==3.0.2)
Requires-Dist: python-cern-sso (==1.3.3)
Requires-Dist: python-slugify (==6.1.2)
